lcm/lcm.vhdl
library ieee;
use ieee.std_logic_1164.all;
use ieee.numeric_std.all;

entity lcm_fsm is
        port (
	reset,clk:in std_logic;
        num1,num2:in integer;
        lcm:out integer
        );        
        
end lcm_fsm;

architecture lcm_arch of lcm_fsm is
	Type state is (START,INPUT,CHECK,UPDATEX,UPDATEY,OUTPUT);
	signal ps,ns:state;
begin
                sl:process(clk,reset)
		begin
			if(reset='1') then
				ps<=start;
			elsif(rising_edge(clk)) then
				ps<=ns;
			end if;
		end process sl;

		cl:process(num1,num2,ps)
			Variable x,y,z:integer;
		begin
			case ps is
				when START=>
					lcm<=10;
					ns<=INPUT;
				when INPUT=>
					x:=num1;
					y:=num2;
					z:=x*y;
					ns<=CHECK;
				when CHECK=>
					if(x>y) then
					ns<=UPDATEX;
						    elsif(x<y) then
							    ns<=UPDATEY;
								else
									ns<=OUTPUT;
					end if;
				when UPDATEX=>
					x:=x-y;
					ns<=CHECK;
				when UPDATEY=>
					y:=y-x;
					ns<=CHECK;
				when OUTPUT=>
					lcm<=z/x;
					ns<=START;
				when OTHERS=>
					ns<=INPUT;
				end case;
			end process cl; 
end lcm_arch;

lcm/lcm_tb.vhdl
library ieee;
use ieee.std_logic_1164.all;

entity lcm_tb is
end lcm_tb;

architecture test of lcm_tb is
	signal clk,reset:std_logic;
	signal num1,num2,lcm:integer;
	component lcm_fsm
		port(
		reset,clk:in std_logic;
        	num1,num2:in integer;
        	lcm:out integer
	);
	end component;
begin
	lcm1:lcm_fsm port map(clk=>clk,reset=>reset,num1=>num1,num2=>num2,lcm=>lcm);
	clock:process 
		variable count:integer;
		begin
			count:=0;
			while count<100 loop
			clk<='1';
			wait for 1 sec;
			clk<='0';
			wait for 1 sec;
			count:=count+1;
		end loop;
		wait;
			end process clock;
	process
	begin
		wait for 100 ns;
		reset<='1';
		num1<=6;
		num2<=4;
		wait for 10 sec;
		reset<='0';
		wait;
	end process;

end test;

lcm/result.vcd
$date
  Sat Feb 10 17:34:23 2024
$end
$version
  GHDL v0
$end
$timescale
  1 fs
$end
$scope module standard $end
$upscope $end
$scope module std_logic_1164 $end
$upscope $end
$scope module numeric_std $end
$upscope $end
$scope module lcm_tb $end
$var reg 1 ! clk $end
$var reg 1 " reset $end
$var integer 32 # num1 $end
$var integer 32 $ num2 $end
$var integer 32 % lcm $end
$scope module lcm1 $end
$var reg 1 & reset $end
$var reg 1 ' clk $end
$var integer 32 ( num1 $end
$var integer 32 ) num2 $end
$var integer 32 * lcm $end
$comment ps is not handled $end
$comment ns is not handled $end
$upscope $end
$upscope $end
$enddefinitions $end
#0
1!
U"
b10000000000000000000000000000000 #
b10000000000000000000000000000000 $
b1010 %
U&
1'
b10000000000000000000000000000000 (
b10000000000000000000000000000000 )
b1010 *
#100000000
1"
b110 #
b100 $
1&
b110 (
b100 )
#1000000000000000
0!
0'
#2000000000000000
1!
1'
#3000000000000000
0!
0'
#4000000000000000
1!
1'
#5000000000000000
0!
0'
#6000000000000000
1!
1'
#7000000000000000
0!
0'
#8000000000000000
1!
1'
#9000000000000000
0!
0'
#10000000000000000
1!
1'
#10000000100000000
0"
0&
#11000000000000000
0!
0'
#12000000000000000
1!
1'
#13000000000000000
0!
0'
#14000000000000000
1!
1'
#15000000000000000
0!
0'
#16000000000000000
1!
1'
#17000000000000000
0!
0'
#18000000000000000
1!
1'
#19000000000000000
0!
0'
#20000000000000000
1!
1'
#21000000000000000
0!
0'
#22000000000000000
1!
1'
#23000000000000000
0!
0'
#24000000000000000
1!
b1100 %
1'
b1100 *
#25000000000000000
0!
0'
#26000000000000000
1!
b1010 %
1'
b1010 *
#27000000000000000
0!
0'
#28000000000000000
1!
1'
#29000000000000000
0!
0'
#30000000000000000
1!
1'
#31000000000000000
0!
0'
#32000000000000000
1!
1'
#33000000000000000
0!
0'
#34000000000000000
1!
1'
#35000000000000000
0!
0'
#36000000000000000
1!
1'
#37000000000000000
0!
0'
#38000000000000000
1!
1'
#39000000000000000
0!
0'
#40000000000000000
1!
b1100 %
1'
b1100 *
#41000000000000000
0!
0'
#42000000000000000
1!
b1010 %
1'
b1010 *
#43000000000000000
0!
0'
#44000000000000000
1!
1'
#45000000000000000
0!
0'
#46000000000000000
1!
1'
#47000000000000000
0!
0'
#48000000000000000
1!
1'
#49000000000000000
0!
0'
#50000000000000000
1!
1'
#51000000000000000
0!
0'
#52000000000000000
1!
1'
#53000000000000000
0!
0'
#54000000000000000
1!
1'
#55000000000000000
0!
0'
#56000000000000000
1!
b1100 %
1'
b1100 *
#57000000000000000
0!
0'
#58000000000000000
1!
b1010 %
1'
b1010 *
#59000000000000000
0!
0'
#60000000000000000
1!
1'
#61000000000000000
0!
0'
#62000000000000000
1!
1'
#63000000000000000
0!
0'
#64000000000000000
1!
1'
#65000000000000000
0!
0'
#66000000000000000
1!
1'
#67000000000000000
0!
0'
#68000000000000000
1!
1'
#69000000000000000
0!
0'
#70000000000000000
1!
1'
#71000000000000000
0!
0'
#72000000000000000
1!
b1100 %
1'
b1100 *
#73000000000000000
0!
0'
#74000000000000000
1!
b1010 %
1'
b1010 *
#75000000000000000
0!
0'
#76000000000000000
1!
1'
#77000000000000000
0!
0'
#78000000000000000
1!
1'
#79000000000000000
0!
0'
#80000000000000000
1!
1'
#81000000000000000
0!
0'
#82000000000000000
1!
1'
#83000000000000000
0!
0'
#84000000000000000
1!
1'
#85000000000000000
0!
0'
#86000000000000000
1!
1'
#87000000000000000
0!
0'
#88000000000000000
1!
b1100 %
1'
b1100 *
#89000000000000000
0!
0'
#90000000000000000
1!
b1010 %
1'
b1010 *
#91000000000000000
0!
0'
#92000000000000000
1!
1'
#93000000000000000
0!
0'
#94000000000000000
1!
1'
#95000000000000000
0!
0'
#96000000000000000
1!
1'
#97000000000000000
0!
0'
#98000000000000000
1!
1'
#99000000000000000
0!
0'
#100000000000000000
1!
1'
#101000000000000000
0!
0'
#102000000000000000
1!
1'
#103000000000000000
0!
0'
#104000000000000000
1!
b1100 %
1'
b1100 *
#105000000000000000
0!
0'
#106000000000000000
1!
b1010 %
1'
b1010 *
#107000000000000000
0!
0'
#108000000000000000
1!
1'
#109000000000000000
0!
0'
#110000000000000000
1!
1'
#111000000000000000
0!
0'
#112000000000000000
1!
1'
#113000000000000000
0!
0'
#114000000000000000
1!
1'
#115000000000000000
0!
0'
#116000000000000000
1!
1'
#117000000000000000
0!
0'
#118000000000000000
1!
1'
#119000000000000000
0!
0'
#120000000000000000
1!
b1100 %
1'
b1100 *
#121000000000000000
0!
0'
#122000000000000000
1!
b1010 %
1'
b1010 *
#123000000000000000
0!
0'
#124000000000000000
1!
1'
#125000000000000000
0!
0'
#126000000000000000
1!
1'
#127000000000000000
0!
0'
#128000000000000000
1!
1'
#129000000000000000
0!
0'
#130000000000000000
1!
1'
#131000000000000000
0!
0'
#132000000000000000
1!
1'
#133000000000000000
0!
0'
#134000000000000000
1!
1'
#135000000000000000
0!
0'
#136000000000000000
1!
b1100 %
1'
b1100 *
#137000000000000000
0!
0'
#138000000000000000
1!
b1010 %
1'
b1010 *
#139000000000000000
0!
0'
#140000000000000000
1!
1'
#141000000000000000
0!
0'
#142000000000000000
1!
1'
#143000000000000000
0!
0'
#144000000000000000
1!
1'
#145000000000000000
0!
0'
#146000000000000000
1!
1'
#147000000000000000
0!
0'
#148000000000000000
1!
1'
#149000000000000000
0!
0'
#150000000000000000
1!
1'
#151000000000000000
0!
0'
#152000000000000000
1!
b1100 %
1'
b1100 *
#153000000000000000
0!
0'
#154000000000000000
1!
b1010 %
1'
b1010 *
#155000000000000000
0!
0'
#156000000000000000
1!
1'
#157000000000000000
0!
0'
#158000000000000000
1!
1'
#159000000000000000
0!
0'
#160000000000000000
1!
1'
#161000000000000000
0!
0'
#162000000000000000
1!
1'
#163000000000000000
0!
0'
#164000000000000000
1!
1'
#165000000000000000
0!
0'
#166000000000000000
1!
1'
#167000000000000000
0!
0'
#168000000000000000
1!
b1100 %
1'
b1100 *
#169000000000000000
0!
0'
#170000000000000000
1!
b1010 %
1'
b1010 *
#171000000000000000
0!
0'
#172000000000000000
1!
1'
#173000000000000000
0!
0'
#174000000000000000
1!
1'
#175000000000000000
0!
0'
#176000000000000000
1!
1'
#177000000000000000
0!
0'
#178000000000000000
1!
1'
#179000000000000000
0!
0'
#180000000000000000
1!
1'
#181000000000000000
0!
0'
#182000000000000000
1!
1'
#183000000000000000
0!
0'
#184000000000000000
1!
b1100 %
1'
b1100 *
#185000000000000000
0!
0'
#186000000000000000
1!
b1010 %
1'
b1010 *
